slacktastic/__init__.py
slacktastic/__main__.py
slacktastic/client.py
slacktastic/constants.py
slacktastic/exceptions.py
slacktastic/template.py
slacktastic-0.3.2.dist-info/AUTHORS.rst
slacktastic-0.3.2.dist-info/LICENSE
slacktastic-0.3.2.dist-info/METADATA
slacktastic-0.3.2.dist-info/WHEEL
slacktastic-0.3.2.dist-info/top_level.txt
slacktastic-0.3.2.dist-info/RECORD
