Metadata-Version: 1.1
Name: slacktastic
Version: 0.3.2
Summary: Package to send Statistics over a Slack Incoming Webhook
Home-page: https://github.com/imperatus/slacktastic
Author: Jurgen Buisman
Author-email: jurgen@labela.nl
License: MIT license
Keywords: slacktastic
Platform: UNKNOWN
Classifier: Development Status :: 2 - Pre-Alpha
Classifier: Intended Audience :: Developers
Classifier: License :: OSI Approved :: MIT License
Classifier: Natural Language :: English
Classifier: Programming Language :: Python :: 3.7
